pydevmgr_elt/__init__.py
pydevmgr_elt/base/__init__.py
pydevmgr_elt/base/config.py
pydevmgr_elt/base/eltdevice.py
pydevmgr_elt/base/eltengine.py
pydevmgr_elt/base/eltinterface.py
pydevmgr_elt/base/eltmanager.py
pydevmgr_elt/base/eltnode.py
pydevmgr_elt/base/eltrpc.py
pydevmgr_elt/base/eltstat.py
pydevmgr_elt/base/io.py
pydevmgr_elt/base/register.py
pydevmgr_elt/base/tools.py
pydevmgr_elt/devices/__init__.py
pydevmgr_elt/devices/adc/__init__.py
pydevmgr_elt/devices/adc/cfg.py
pydevmgr_elt/devices/adc/rpcs.py
pydevmgr_elt/devices/adc/stat.py
pydevmgr_elt/devices/ccssim/__init__.py
pydevmgr_elt/devices/ccssim/cfg.py
pydevmgr_elt/devices/ccssim/ctrl.py
pydevmgr_elt/devices/ccssim/rpcs.py
pydevmgr_elt/devices/ccssim/stat.py
pydevmgr_elt/devices/drot/__init__.py
pydevmgr_elt/devices/drot/cfg.py
pydevmgr_elt/devices/drot/rpcs.py
pydevmgr_elt/devices/drot/stat.py
pydevmgr_elt/devices/lamp/__init__.py
pydevmgr_elt/devices/lamp/cfg.py
pydevmgr_elt/devices/lamp/rpcs.py
pydevmgr_elt/devices/lamp/stat.py
pydevmgr_elt/devices/motor/__init__.py
pydevmgr_elt/devices/motor/axis_type.py
pydevmgr_elt/devices/motor/cfg.py
pydevmgr_elt/devices/motor/init_seq.py
pydevmgr_elt/devices/motor/positions.py
pydevmgr_elt/devices/motor/rpcs.py
pydevmgr_elt/devices/motor/stat.py
pydevmgr_elt/devices/piezo/__init__.py
pydevmgr_elt/devices/piezo/cfg.py
pydevmgr_elt/devices/piezo/rpcs.py
pydevmgr_elt/devices/piezo/stat.py
pydevmgr_elt/devices/sensor/__init__.py
pydevmgr_elt/devices/sensor/aiChannels.py
pydevmgr_elt/devices/sensor/aoChannels.py
pydevmgr_elt/devices/sensor/cfg.py
pydevmgr_elt/devices/sensor/channel.py
pydevmgr_elt/devices/sensor/diChannels.py
pydevmgr_elt/devices/sensor/doChannels.py
pydevmgr_elt/devices/sensor/rpcs.py
pydevmgr_elt/devices/sensor/stat.py
pydevmgr_elt/devices/shutter/__init__.py
pydevmgr_elt/devices/shutter/cfg.py
pydevmgr_elt/devices/shutter/rpcs.py
pydevmgr_elt/devices/shutter/stat.py
pydevmgr_elt/devices/time/__init__.py
pydevmgr_elt/devices/time/cfg.py
pydevmgr_elt-0.6a6.dist-info/WHEEL
pydevmgr_elt-0.6a6.dist-info/entry_points.txt
pydevmgr_elt-0.6a6.dist-info/METADATA
pydevmgr_elt-0.6a6.dist-info/RECORD
