Metadata-Version: 2.1
Name: pydevmgr-elt
Version: 0.6a6
Summary: pydevmgr pluggin for Elt devices
License: CECILL-2.1
Author: Sylvain Guieu
Author-email: sylvain.guieu@univ-grenoble-alpes.fr
Requires-Python: >=3.7,<4.0
Classifier: License :: OSI Approved :: CEA CNRS Inria Logiciel Libre License, version 2.1 (CeCILL-2.1)
Classifier: Programming Language :: Python :: 3
Classifier: Programming Language :: Python :: 3.7
Classifier: Programming Language :: Python :: 3.8
Classifier: Programming Language :: Python :: 3.9
Classifier: Programming Language :: Python :: 3.10
Classifier: Programming Language :: Python :: 3.11
Requires-Dist: jinja2 (>=3.1.2,<4.0.0)
Requires-Dist: pydevmgr-ua (==0.6.a4)
